bin/FastTree
bin/add-chimeras.py
bin/add-seqs-to-outputs.py
bin/bcr-phylo-run.py
bin/build.sh
bin/cf-alleles.py
bin/cf-germlines.py
bin/cf-linearham.py
bin/chimera-plot.py
bin/choose-partially-paired.py
bin/circle-plots.py
bin/compare-plotdirs.py
bin/diff-parameters.py
bin/docker-hub-push.sh
bin/extract-pairing-info.py
bin/gcdyn-simu-run.py
bin/gctree-run.py
bin/get-naive-probabilities.py
bin/iqtree-1.6.12
bin/lonr.r
bin/makeHtml
bin/mds-run.py
bin/parse-output.py
bin/partis
bin/partis-pip
bin/partis.py
bin/plot-gl-set-trees.py
bin/plot-hmms.py
bin/plot-lb-tree.py
bin/raxml-ng
bin/read-bcr-phylo-trees.py
bin/read-gctree-output.py
bin/run-chimeras.sh
bin/run-dtr-scan.sh
bin/run-paired-loci.sh
bin/run-tree-metrics.sh
bin/smetric-run.py
bin/split-loci.py
bin/swarm-2.1.13-linux-x86_64
bin/test-germline-inference.py
bin/tree-perf-run.py
bin/vsearch-2.4.3-linux-x86_64
bin/vsearch-2.4.3-macos-x86_64
bin/xvfb-run
data/gizmod.txt
data/notes.txt
data/sample-seqs.yaml
data/fam-alignments/ighd-aligned.fasta
data/fam-alignments/ighj-aligned.fasta
data/fam-alignments/ighv-aligned.fasta
data/germlines/README.md
data/germlines/parse-ogrdb.py
data/germlines/balbc/igh/extras.csv
data/germlines/balbc/igh/ighd.fasta
data/germlines/balbc/igh/ighj.fasta
data/germlines/balbc/igh/ighv.fasta
data/germlines/balbc/igk/extras.csv
data/germlines/balbc/igk/igkj.fasta
data/germlines/balbc/igk/igkv.fasta
data/germlines/balbc/igl/extras.csv
data/germlines/balbc/igl/iglj.fasta
data/germlines/balbc/igl/iglv.fasta
data/germlines/c57bl/igh/extras.csv
data/germlines/c57bl/igh/ighd.fasta
data/germlines/c57bl/igh/ighj.fasta
data/germlines/c57bl/igh/ighv.fasta
data/germlines/c57bl/igk/extras.csv
data/germlines/c57bl/igk/igkj.fasta
data/germlines/c57bl/igk/igkv.fasta
data/germlines/c57bl/igl/extras.csv
data/germlines/c57bl/igl/iglj.fasta
data/germlines/c57bl/igl/iglv.fasta
data/germlines/ch17/notes
data/germlines/ch17/watson-all-genes.csv
data/germlines/ch17/igh/extras.csv
partis_bcr-1.0.4.dist-info/licenses/COPYING
partis_bcr-1.0.4.dist-info/METADATA
partis_bcr-1.0.4.dist-info/WHEEL
partis_bcr-1.0.4.dist-info/entry_points.txt
partis_bcr-1.0.4.dist-info/top_level.txt
partis_bcr-1.0.4.dist-info/RECORD
