Metadata-Version: 2.4
Name: partis-bcr
Version: 1.0.4
Summary: B- and T-cell receptor sequence annotation, simulation, clonal family and germline inference
Home-page: https://github.com/psathyrella/partis
Author: Duncan Ralph
Author-email: dkralph@gmail.com
License: GPL-3.0
Project-URL: Bug Reports, https://github.com/psathyrella/partis/issues
Project-URL: Source, https://github.com/psathyrella/partis
Project-URL: Documentation, https://github.com/psathyrella/partis/tree/main/docs
Keywords: immunology bioinformatics bcr tcr antibody sequence-analysis
Classifier: Development Status :: 4 - Beta
Classifier: Intended Audience :: Science/Research
Classifier: Topic :: Scientific/Engineering :: Bio-Informatics
Classifier: License :: OSI Approved :: GNU General Public License v3 (GPLv3)
Classifier: Programming Language :: Python :: 3
Classifier: Programming Language :: Python :: 3.7
Classifier: Programming Language :: Python :: 3.8
Classifier: Programming Language :: Python :: 3.9
Classifier: Programming Language :: Python :: 3.10
Classifier: Programming Language :: Python :: 3.11
Requires-Python: >=3.7
License-File: COPYING
Requires-Dist: biopython
Requires-Dist: colored-traceback
Requires-Dist: dendropy
Requires-Dist: matplotlib
Requires-Dist: numpy
Requires-Dist: pandas
Requires-Dist: psutil
Requires-Dist: pysam
Requires-Dist: PyYAML
Requires-Dist: scikit-learn
Requires-Dist: scipy
Requires-Dist: seaborn
Requires-Dist: six
Provides-Extra: plotting
Requires-Dist: circlify; extra == "plotting"
Requires-Dist: ete3; extra == "plotting"
Requires-Dist: joypy; extra == "plotting"
Requires-Dist: matplotlib; extra == "plotting"
Provides-Extra: full
Requires-Dist: circlify; extra == "full"
Requires-Dist: ete3; extra == "full"
Requires-Dist: joypy; extra == "full"
Requires-Dist: levenshtein; extra == "full"
Requires-Dist: matplotlib; extra == "full"
Dynamic: author
Dynamic: author-email
Dynamic: classifier
Dynamic: description
Dynamic: description-content-type
Dynamic: home-page
Dynamic: keywords
Dynamic: license
Dynamic: license-file
Dynamic: project-url
Dynamic: provides-extra
Dynamic: requires-dist
Dynamic: requires-python
Dynamic: summary
